MANIFEST.in
README.txt
setup.py
bcmwindow/__init__.py
bcmwindow/bcm.py
bcmwindow/tests.py
bcmwindow/version.py
bcmwindow.egg-info/PKG-INFO
bcmwindow.egg-info/SOURCES.txt
bcmwindow.egg-info/dependency_links.txt
bcmwindow.egg-info/entry_points.txt
bcmwindow.egg-info/top_level.txt
examples/raw.py