Metadata-Version: 1.1
Name: bcmwindow
Version: 1.0.0
Summary: bcmwindow
Home-page: https://github.com/mcfletch/bcmwindow
Author: Mike C. Fletcher
Author-email: mcfletch@vrplumber.com
License: BSD
Keywords: raspberry pi,window,opengl,gles,egl
Platform: UNKNOWN
Classifier: Programming Language :: Python
